ripemd_hash-1.0.0.dist-info/LICENSE.rst
ripemd_hash-1.0.0.dist-info/METADATA
ripemd_hash-1.0.0.dist-info/WHEEL
ripemd_hash-1.0.0.dist-info/top_level.txt
ripemd_hash-1.0.0.dist-info/RECORD
ripemd/_ripemd160.abi3.so
ripemd/_raw_api.py
ripemd/ripemd160.py
ripemd/__init__.py
